igv_reports/__init__.py
igv_reports/bam.py
igv_reports/bedtable.py
igv_reports/chr_alias.py
igv_reports/chralias.py
igv_reports/compress.py
igv_reports/datauri.py
igv_reports/fasta.py
igv_reports/feature.py
igv_reports/featureTree.py
igv_reports/generictable.py
igv_reports/genome.py
igv_reports/ideogram.py
igv_reports/regions.py
igv_reports/report.py
igv_reports/stream.py
igv_reports/tracks.py
igv_reports/twobit.py
igv_reports/utils.py
igv_reports/varianttable.py
igv_reports/vcf.py
igv_reports/wig.py
igv_reports/__pycache__/__init__.cpython-39.pyc
igv_reports/__pycache__/stream.cpython-39.pyc
igv_reports/templates/fusion_template.html
igv_reports/templates/junction_template.html
igv_reports/templates/variant_template-2.html
igv_reports/templates/variant_template-noembed.html
igv_reports/templates/variant_template.html
igv_reports/templates/variant_template_tabulator.html
igv_reports-1.16.1.dist-info/LICENSE.md
igv_reports-1.16.1.dist-info/METADATA
igv_reports-1.16.1.dist-info/WHEEL
igv_reports-1.16.1.dist-info/entry_points.txt
igv_reports-1.16.1.dist-info/top_level.txt
igv_reports-1.16.1.dist-info/RECORD
