Metadata-Version: 2.1
Name: igv-reports
Version: 1.16.1
Summary: Creates self-contained html pages for visual variant review with IGV (igv.js).
Home-page: https://github.com/igvteam/igv-reports
Author: Jim Robinson
License: MIT
Keywords: igv,bioinformatics,genomics,visualization,variant
Platform: UNKNOWN
Classifier: Programming Language :: Python :: 3
Classifier: Development Status :: 4 - Beta 
Classifier: Intended Audience :: Science/Research
Classifier: Intended Audience :: Developers
Classifier: License :: OSI Approved :: MIT License
Classifier: Topic :: Scientific/Engineering :: Bio-Informatics 
Requires-Dist: pysam
Requires-Dist: intervalTree
Requires-Dist: requests
Requires-Dist: pytwobit
Requires-Dist: pyyaml
